tse_derivatives/__init__.py
tse_derivatives-0.1.4.dist-info/METADATA
tse_derivatives-0.1.4.dist-info/WHEEL
tse_derivatives-0.1.4.dist-info/top_level.txt
tse_derivatives-0.1.4.dist-info/RECORD
