Metadata-Version: 2.1
Name: tse-derivatives
Version: 0.1.4
Summary: Gets the underlying asset ticker and the option type (either call or put) to fetch live option data.
Author: Jalal Seifoddini
Author-email: jalal.seifoddini@gmail.com
Classifier: Programming Language :: Python :: 3
Classifier: License :: OSI Approved :: MIT License
Classifier: Operating System :: OS Independent
Requires-Python: >=3.6
Requires-Dist: requests
Requires-Dist: pandas
